odoo10_addon_mrp_no_partial-10.0.1.0.1-nspkg.pth
odoo/addons/mrp_no_partial/README.rst
odoo/addons/mrp_no_partial/__init__.py
odoo/addons/mrp_no_partial/__manifest__.py
odoo/addons/mrp_no_partial/i18n/mrp_no_partial.pot
odoo/addons/mrp_no_partial/models/__init__.py
odoo/addons/mrp_no_partial/models/mrp_production.py
odoo/addons/mrp_no_partial/models/stock_picking_type.py
odoo/addons/mrp_no_partial/readme/CONTRIBUTORS.rst
odoo/addons/mrp_no_partial/readme/DESCRIPTION.rst
odoo/addons/mrp_no_partial/readme/HISTORY.rst
odoo/addons/mrp_no_partial/readme/USAGE.rst
odoo/addons/mrp_no_partial/static/description/icon.png
odoo/addons/mrp_no_partial/static/description/index.html
odoo/addons/mrp_no_partial/tests/__init__.py
odoo/addons/mrp_no_partial/tests/test_no_partial.py
odoo/addons/mrp_no_partial/views/stock_picking_type.xml
odoo/addons/mrp_no_partial/wizards/__init__.py
odoo/addons/mrp_no_partial/wizards/mrp_product_produce.py
odoo10_addon_mrp_no_partial-10.0.1.0.1.dist-info/METADATA
odoo10_addon_mrp_no_partial-10.0.1.0.1.dist-info/WHEEL
odoo10_addon_mrp_no_partial-10.0.1.0.1.dist-info/namespace_packages.txt
odoo10_addon_mrp_no_partial-10.0.1.0.1.dist-info/top_level.txt
odoo10_addon_mrp_no_partial-10.0.1.0.1.dist-info/RECORD
