Metadata-Version: 2.1
Name: odoo10-addon-mrp-no-partial
Version: 10.0.1.0.1
Summary: Block the production order if all quantities are not done
Home-page: https://github.com/OCA/manufacture
Author: ACSONE SA/NV,Odoo Community Association (OCA)
Author-email: support@odoo-community.org
License: AGPL-3
Platform: UNKNOWN
Classifier: Programming Language :: Python
Classifier: Framework :: Odoo
Classifier: License :: OSI Approved :: GNU Affero General Public License v3
Requires-Python: ~=2.7
Requires-Dist: odoo (<10.1dev,>=10.0)
